{
  "publicPath": "/_nuxt/",
  "all": [
    "../server/index.spa.html",
    "../server/index.ssr.html",
    "09b4e1f.js",
    "0e0f354.js",
    "1e44eef.js",
    "1fc29d5.js",
    "2083a7f.js",
    "21a6f93.js",
    "2c8df9b.js",
    "3288e1a.js",
    "359c5f1.js",
    "3631729.js",
    "381cff8.js",
    "4439e6a.js",
    "4f381d3.js",
    "4fe7336.js",
    "5369629.js",
    "5d22f7a.js",
    "5e0ac24.js",
    "639cbc2.js",
    "7481c7a.js",
    "772f257.js",
    "87ca3e7.js",
    "8f935e8.js",
    "LICENSES",
    "a809158.js",
    "b781eec.js",
    "c92aa27.js",
    "c9697ac.js",
    "css/03772b7.css",
    "css/0ce42a2.css",
    "css/0f5e3d4.css",
    "css/175a8c7.css",
    "css/1ad3614.css",
    "css/20ea3aa.css",
    "css/346f61f.css",
    "css/3f3ff38.css",
    "css/46e7638.css",
    "css/46f6e5b.css",
    "css/557941f.css",
    "css/6fd557d.css",
    "css/7833771.css",
    "css/a4e71cb.css",
    "css/aac3bcf.css",
    "css/ba9efcb.css",
    "css/bf145a1.css",
    "css/c823262.css",
    "css/e0b1e27.css",
    "css/e32fb7e.css",
    "css/e5cc4fb.css",
    "d5539ee.js",
    "db80ac9.js",
    "e055d4c.js",
    "ef9c136.js",
    "img/clio.a2c92b8.jpg",
    "img/icon-ec.3feab34.png",
    "img/landing-1.0dfef06.jpg",
    "img/landing-2.2170b7b.jpg",
    "img/lucas.fd779f5.jpg",
    "img/mail.66b170b.jpg",
    "img/menu-1-small.b63d675.jpg",
    "img/menu-1.cbb7494.jpg",
    "img/menu-2-small.9229bd2.jpg",
    "img/menu-2.75e8172.jpg",
    "img/menu-3-small.94af287.jpg",
    "img/menu-3.e41c00b.jpg",
    "img/menu-4-small.046a4b3.jpg",
    "img/menu-4.3a46d14.jpg",
    "img/vill.8e765fd.jpeg",
    "img/whatsapp.bfe6cb7.jpg"
  ],
  "initial": [
    "21a6f93.js",
    "8f935e8.js",
    "css/46f6e5b.css",
    "c92aa27.js",
    "css/aac3bcf.css",
    "87ca3e7.js"
  ],
  "async": [
    "09b4e1f.js",
    "0e0f354.js",
    "1e44eef.js",
    "1fc29d5.js",
    "2083a7f.js",
    "2c8df9b.js",
    "3288e1a.js",
    "359c5f1.js",
    "3631729.js",
    "381cff8.js",
    "4439e6a.js",
    "4f381d3.js",
    "4fe7336.js",
    "5369629.js",
    "5d22f7a.js",
    "5e0ac24.js",
    "639cbc2.js",
    "7481c7a.js",
    "772f257.js",
    "a809158.js",
    "b781eec.js",
    "c9697ac.js",
    "css/03772b7.css",
    "css/0ce42a2.css",
    "css/0f5e3d4.css",
    "css/175a8c7.css",
    "css/1ad3614.css",
    "css/20ea3aa.css",
    "css/346f61f.css",
    "css/3f3ff38.css",
    "css/46e7638.css",
    "css/557941f.css",
    "css/6fd557d.css",
    "css/7833771.css",
    "css/a4e71cb.css",
    "css/ba9efcb.css",
    "css/bf145a1.css",
    "css/c823262.css",
    "css/e0b1e27.css",
    "css/e32fb7e.css",
    "css/e5cc4fb.css",
    "d5539ee.js",
    "db80ac9.js",
    "e055d4c.js",
    "ef9c136.js"
  ],
  "modules": {
    "15056928": [
      23
    ],
    "15202850": [
      23
    ],
    "17853052": [
      23
    ],
    "47273782": [
      38,
      27
    ],
    "56738129": [
      23
    ],
    "64672201": [
      23
    ],
    "64830396": [
      23
    ],
    "72995325": [
      23
    ],
    "309832e0": [
      43,
      22,
      55,
      61,
      63,
      65,
      67,
      60,
      62,
      64,
      66
    ],
    "6ef872b2": [
      23
    ],
    "4b1061e9": [
      23
    ],
    "683da564": [
      23
    ],
    "5dd247eb": [
      23
    ],
    "6c58fa02": [
      23
    ],
    "bede1d66": [
      23
    ],
    "363156f2": [
      23
    ],
    "6f152030": [
      23
    ],
    "72d4cbec": [
      23
    ],
    "10bbf972": [
      23
    ],
    "775563c6": [
      23
    ],
    "01c500b1": [
      23
    ],
    "79e3a936": [
      23
    ],
    "b5224fa4": [
      23
    ],
    "4d40bed4": [
      23
    ],
    "c4fb0392": [
      23
    ],
    "4a1f746e": [
      23
    ],
    "3a665a54": [
      23
    ],
    "1a67dd14": [
      23
    ],
    "372b8d72": [
      23
    ],
    "0495e93f": [
      23
    ],
    "e1d8cc28": [
      23
    ],
    "8e5ba30e": [
      23
    ],
    "4d139847": [
      23
    ],
    "ded30cf2": [
      23
    ],
    "70b62bca": [
      23
    ],
    "544ffeb5": [
      23
    ],
    "826b8d3e": [
      23
    ],
    "b3b3e79e": [
      23
    ],
    "f87146aa": [
      23
    ],
    "d6c4151a": [
      23
    ],
    "53d139ed": [
      23
    ],
    "0bbc1b1f": [
      43,
      22,
      55,
      61,
      63,
      65,
      67,
      60,
      62,
      64,
      66
    ],
    "b3f573d8": [
      43,
      22,
      55,
      61,
      63,
      65,
      67,
      60,
      62,
      64,
      66
    ],
    "412e16e6": [
      43,
      22,
      55,
      61,
      63,
      65,
      67,
      60,
      62,
      64,
      66
    ],
    "7c2f13b7": [
      43,
      22,
      55,
      61,
      63,
      65,
      67,
      60,
      62,
      64,
      66
    ],
    "8047e656": [
      43,
      22,
      55,
      61,
      63,
      65,
      67,
      60,
      62,
      64,
      66
    ],
    "7dd08610": [
      43,
      22,
      55,
      61,
      63,
      65,
      67,
      60,
      62,
      64,
      66
    ],
    "6b611cb0": [
      43,
      22,
      55,
      61,
      63,
      65,
      67,
      60,
      62,
      64,
      66
    ],
    "09090a65": [
      43,
      22,
      55,
      61,
      63,
      65,
      67,
      60,
      62,
      64,
      66
    ],
    "679a184b": [
      43,
      22,
      55,
      61,
      63,
      65,
      67,
      60,
      62,
      64,
      66
    ],
    "742bbcf3": [
      43,
      22,
      55,
      61,
      63,
      65,
      67,
      60,
      62,
      64,
      66
    ],
    "aeba3768": [
      43,
      22,
      55,
      61,
      63,
      65,
      67,
      60,
      62,
      64,
      66
    ],
    "770a352d": [
      43,
      22,
      55,
      61,
      63,
      65,
      67,
      60,
      62,
      64,
      66
    ],
    "1f7f7a7c": [
      43,
      22,
      55,
      61,
      63,
      65,
      67,
      60,
      62,
      64,
      66
    ],
    "10ee06d3": [
      43,
      22,
      55,
      61,
      63,
      65,
      67,
      60,
      62,
      64,
      66
    ],
    "b9e001aa": [
      43,
      22,
      55,
      61,
      63,
      65,
      67,
      60,
      62,
      64,
      66
    ],
    "296a3479": [
      43,
      22,
      55,
      61,
      63,
      65,
      67,
      60,
      62,
      64,
      66
    ],
    "7806c9f6": [
      43,
      22,
      55,
      61,
      63,
      65,
      67,
      60,
      62,
      64,
      66
    ],
    "3a41a0c4": [
      43,
      22,
      55,
      61,
      63,
      65,
      67,
      60,
      62,
      64,
      66
    ],
    "14ca3bfa": [
      43,
      22,
      55,
      61,
      63,
      65,
      67,
      60,
      62,
      64,
      66
    ],
    "89cbe9ba": [
      43,
      22,
      55,
      61,
      63,
      65,
      67,
      60,
      62,
      64,
      66
    ],
    "d8ff2950": [
      43,
      22,
      55,
      61,
      63,
      65,
      67,
      60,
      62,
      64,
      66
    ],
    "1162a352": [
      43,
      22,
      55,
      61,
      63,
      65,
      67,
      60,
      62,
      64,
      66
    ],
    "6c26da29": [
      43,
      22,
      55,
      61,
      63,
      65,
      67,
      60,
      62,
      64,
      66
    ],
    "0fbfe09f": [
      43,
      22,
      55,
      61,
      63,
      65,
      67,
      60,
      62,
      64,
      66
    ],
    "106643c3": [
      43,
      22,
      55,
      61,
      63,
      65,
      67,
      60,
      62,
      64,
      66
    ],
    "120bd85e": [
      43,
      22,
      55,
      61,
      63,
      65,
      67,
      60,
      62,
      64,
      66
    ],
    "ffdd9316": [
      43,
      22,
      55,
      61,
      63,
      65,
      67,
      60,
      62,
      64,
      66
    ],
    "49cf7d99": [
      43,
      22,
      55,
      61,
      63,
      65,
      67,
      60,
      62,
      64,
      66
    ],
    "0104b827": [
      43,
      22,
      55,
      61,
      63,
      65,
      67,
      60,
      62,
      64,
      66
    ],
    "23771e32": [
      23
    ],
    "b155b2f2": [
      23
    ],
    "0d62b1f7": [
      23
    ],
    "59c40923": [
      23
    ],
    "cad6ac60": [
      23
    ],
    "ddf42198": [
      23
    ],
    "7459eeee": [
      23
    ],
    "85fb6ae0": [
      23
    ],
    "806473a8": [
      23
    ],
    "312df33c": [
      23
    ],
    "7b5eb096": [
      23
    ],
    "ded741b2": [
      23
    ],
    "1b168b32": [
      23
    ],
    "625ac20c": [
      23
    ],
    "a767c894": [
      38,
      27
    ],
    "3a588454": [
      23
    ],
    "00943cf4": [
      23
    ],
    "6b402662": [
      23
    ],
    "d87c2588": [
      23
    ],
    "2ed92ad0": [
      23
    ],
    "4358dea7": [
      23
    ],
    "af0256fc": [
      23
    ],
    "f025cb6c": [
      23
    ],
    "7ae1e955": [
      23
    ],
    "55ea6c2f": [
      23
    ],
    "8451f0fe": [
      23
    ],
    "05af374c": [
      23
    ],
    "9c2c2ac6": [
      23
    ],
    "3ddc3184": [
      23
    ],
    "4dd589cb": [
      23
    ],
    "5c1f2507": [
      23
    ],
    "ae9335e6": [
      23
    ],
    "27ef58aa": [
      23
    ],
    "546f0afd": [
      23
    ],
    "e7490c96": [
      23
    ],
    "9b615820": [
      23
    ],
    "699fff0c": [
      23
    ],
    "2a5b8d94": [
      23
    ],
    "27d5a044": [
      23
    ],
    "c4981484": [
      23
    ],
    "848615fa": [
      23
    ],
    "dcda747a": [
      23
    ],
    "0dcff4fb": [
      23
    ],
    "6cc110aa": [
      23
    ],
    "4f5196cb": [
      23
    ],
    "7cd4ba57": [
      23
    ],
    "69e51c84": [
      23
    ],
    "152dbcbc": [
      23
    ],
    "7cb0bbe8": [
      23
    ],
    "f8e0b6ba": [
      43,
      22,
      55,
      61,
      63,
      65,
      67,
      60,
      62,
      64,
      66
    ],
    "10dd328f": [
      23
    ],
    "0574d1d4": [
      23
    ],
    "5983a7e4": [
      23
    ],
    "2754e3fc": [
      23
    ],
    "7dcd503e": [
      23
    ],
    "6ab59c73": [
      23
    ],
    "658a743d": [
      23
    ],
    "7a7a0c30": [
      23
    ],
    "d2ba2d84": [
      23
    ],
    "d92aafc6": [
      23
    ],
    "2f58485a": [
      23
    ],
    "5935e678": [
      23
    ],
    "6e3f2931": [
      23
    ],
    "dcb2e212": [
      23
    ],
    "27493ac3": [
      23
    ],
    "559b0808": [
      23
    ],
    "1b724d33": [
      23
    ],
    "1d79d800": [
      23
    ],
    "3b840192": [
      23
    ],
    "73664dd2": [
      23
    ],
    "c44022c6": [
      23
    ],
    "045c6d9f": [
      23
    ],
    "e94d95f2": [
      23
    ],
    "37d11721": [
      23
    ],
    "fdb1d206": [
      23
    ],
    "73307faa": [
      43,
      22,
      55,
      61,
      63,
      65,
      67,
      60,
      62,
      64,
      66
    ],
    "0e4d2088": [
      38,
      27
    ],
    "737154f0": [
      23
    ],
    "f1f8c2aa": [
      23
    ],
    "4cf04764": [
      23
    ],
    "86cc3df2": [
      23
    ],
    "a3c6bc06": [
      23
    ],
    "3e027cda": [
      23
    ],
    "4e466063": [
      23
    ],
    "5eebb270": [
      23
    ],
    "35c64ca4": [
      23
    ],
    "64df6809": [
      23
    ],
    "12a694d9": [
      23
    ],
    "5426916a": [
      23
    ],
    "709ac82a": [
      23
    ],
    "26f608b7": [
      23
    ],
    "05e6f133": [
      23
    ],
    "cb95d01a": [
      23
    ],
    "32f317b9": [
      23
    ],
    "1bd1168c": [
      23
    ],
    "67b74e80": [
      23
    ],
    "29f01e7b": [
      23
    ],
    "6b7ad7b6": [
      23
    ],
    "bc218da0": [
      23
    ],
    "4bd66500": [
      23
    ],
    "bdb4ee4a": [
      23
    ],
    "fcae56c6": [
      23
    ],
    "1b490117": [
      23
    ],
    "faecc55c": [
      23
    ],
    "4b32cc6a": [
      23
    ],
    "4d3be8a2": [
      23
    ],
    "48453e54": [
      23
    ],
    "7bb01f2e": [
      23
    ],
    "420374be": [
      23
    ],
    "437326cc": [
      23
    ],
    "27628f36": [
      23
    ],
    "cddf5524": [
      23
    ],
    "61e837bc": [
      23
    ],
    "539f7aae": [
      23
    ],
    "3ef271dc": [
      43,
      22,
      55,
      61,
      63,
      65,
      67,
      60,
      62,
      64,
      66
    ],
    "85c94bb0": [
      43,
      22,
      55,
      61,
      63,
      65,
      67,
      60,
      62,
      64,
      66
    ],
    "e729c80c": [
      43,
      22,
      55,
      61,
      63,
      65,
      67,
      60,
      62,
      64,
      66
    ],
    "47195df1": [
      43,
      22,
      55,
      61,
      63,
      65,
      67,
      60,
      62,
      64,
      66
    ],
    "33b4225a": [
      43,
      22,
      55,
      61,
      63,
      65,
      67,
      60,
      62,
      64,
      66
    ],
    "1ebd89a7": [
      38,
      27
    ],
    "fd081da6": [
      38,
      27
    ],
    "b9225f84": [
      43,
      22,
      55,
      61,
      63,
      65,
      67,
      60,
      62,
      64,
      66
    ],
    "9b06fb9c": [
      43,
      22,
      55,
      61,
      63,
      65,
      67,
      60,
      62,
      64,
      66
    ],
    "9380fc48": [
      43,
      22,
      55,
      61,
      63,
      65,
      67,
      60,
      62,
      64,
      66
    ],
    "6cc431ad": [
      38,
      27
    ],
    "bf25ac56": [
      43,
      22,
      55,
      61,
      63,
      65,
      67,
      60,
      62,
      64,
      66
    ],
    "2a2cca50": [
      38,
      27
    ],
    "741e83a8": [
      38,
      27
    ],
    "e0954606": [
      38,
      27
    ],
    "5e21b584": [
      38,
      27
    ],
    "3b0140d3": [
      38,
      27
    ],
    "643bd290": [
      38,
      27
    ],
    "76b83d04": [
      38,
      27
    ],
    "6a17aa0c": [
      38,
      27
    ],
    "332586f3": [
      38,
      27
    ],
    "5c88a044": [
      38,
      27
    ],
    "4c4f787a": [
      38,
      27
    ],
    "5f1d5be8": [
      38,
      27
    ],
    "0e80fe4c": [
      38,
      27
    ],
    "64b7fa22": [
      38,
      27
    ],
    "28c0316e": [
      38,
      27
    ],
    "290d0509": [
      38,
      27
    ],
    "da240642": [
      38,
      27
    ],
    "287cd2ae": [
      38,
      27
    ],
    "a8f29e5c": [
      38,
      27
    ],
    "4ebb3e48": [
      38,
      27
    ],
    "b3049654": [
      38,
      27
    ],
    "3301cef4": [
      38,
      27
    ],
    "1ff7b046": [
      38,
      27
    ],
    "5b47490d": [
      38,
      27
    ],
    "b9e1c9a0": [
      38,
      27
    ],
    "32748f94": [
      38,
      27
    ],
    "fe75f8fa": [
      38,
      27
    ],
    "18da4b08": [
      38,
      27
    ],
    "c8ec3ab8": [
      38,
      27
    ],
    "03895c0a": [
      38,
      27
    ],
    "27cefdb0": [
      38,
      27
    ],
    "63a679da": [
      38,
      27
    ],
    "1f88ddb2": [
      38,
      27
    ],
    "3f869858": [
      38,
      27
    ],
    "563a51b6": [
      38,
      27
    ],
    "779e7235": [
      38,
      27
    ],
    "40a552e6": [
      38,
      27
    ],
    "b5b70f26": [
      38,
      27
    ],
    "4414a882": [
      38,
      27
    ],
    "78ea878a": [
      38,
      27
    ],
    "034c32d6": [
      38,
      27
    ],
    "44d32f01": [
      38,
      27
    ],
    "452ac461": [
      38,
      27
    ],
    "6c3eeedc": [
      38,
      27
    ],
    "17795e61": [
      38,
      27
    ],
    "d84ee97c": [
      38,
      27
    ],
    "2b952c92": [
      38,
      27
    ],
    "2559ce5f": [
      38,
      27
    ],
    "219aa287": [
      38,
      27
    ],
    "b1c4f568": [
      38,
      27
    ],
    "3551c320": [
      38,
      27
    ],
    "561b1674": [
      38,
      27
    ],
    "3725e3e9": [
      38,
      27
    ],
    "1c33146b": [
      38,
      27
    ],
    "4191cef2": [
      38,
      27
    ],
    "7fd6e310": [
      38,
      27
    ],
    "08a5837e": [
      38,
      27
    ],
    "78ab83db": [
      38,
      27
    ],
    "a3e65d90": [
      38,
      27
    ],
    "23cdf458": [
      38,
      27
    ],
    "0ff2b1ee": [
      38,
      27
    ],
    "e553fa72": [
      38,
      27
    ],
    "0084fd48": [
      38,
      27
    ],
    "a6180588": [
      38,
      27
    ],
    "92e86a1e": [
      38,
      27
    ],
    "5d363e4a": [
      38,
      27
    ],
    "4af61abf": [
      38,
      27
    ],
    "d50c296a": [
      38,
      27
    ],
    "1babe26a": [
      38,
      27
    ],
    "7b3b5f76": [
      43,
      22,
      55,
      61,
      63,
      65,
      67,
      60,
      62,
      64,
      66
    ],
    "8edf1b0e": [
      38,
      27
    ],
    "2a7b8252": [
      43,
      22,
      55,
      61,
      63,
      65,
      67,
      60,
      62,
      64,
      66
    ],
    "677a29a2": [
      23
    ],
    "ca0943b4": [
      23
    ],
    "67419b09": [
      23
    ],
    "00335890": [
      23
    ],
    "3b740512": [
      23
    ],
    "aba018ba": [
      23
    ],
    "4bf0c0b3": [
      23
    ],
    "3f1985e3": [
      23
    ],
    "1ce368cb": [
      23
    ],
    "1c4634c8": [
      23
    ],
    "1dec4275": [
      23
    ],
    "4bb3c503": [
      23
    ],
    "56696de6": [
      23
    ],
    "4fd6c269": [
      23
    ],
    "5b237d8c": [
      23
    ],
    "6aa3d952": [
      23
    ],
    "26c701a4": [
      23
    ],
    "2d4edb10": [
      23
    ],
    "7a8d1906": [
      23
    ],
    "3e3e82a2": [
      23
    ],
    "0803a49b": [
      23
    ],
    "790d2456": [
      23
    ],
    "79ce2f9e": [
      23
    ],
    "2a8d604c": [
      23
    ],
    "060815da": [
      23
    ],
    "2b958e9e": [
      23
    ],
    "9fc467da": [
      23
    ],
    "40f6dc06": [
      23
    ],
    "f36a1c62": [
      23
    ],
    "5fcc42c8": [
      23
    ],
    "5410fbc6": [
      23
    ],
    "0a6e1f1d": [
      23
    ],
    "7fd7352c": [
      23
    ],
    "113247f4": [
      43,
      22,
      55,
      61,
      63,
      65,
      67,
      60,
      62,
      64,
      66
    ],
    "0283eb80": [
      43,
      22,
      55,
      61,
      63,
      65,
      67,
      60,
      62,
      64,
      66
    ],
    "6bd71d76": [
      38,
      27
    ],
    "d4ab673e": [
      43,
      22,
      55,
      61,
      63,
      65,
      67,
      60,
      62,
      64,
      66
    ],
    "c38667ee": [
      43,
      22,
      55,
      61,
      63,
      65,
      67,
      60,
      62,
      64,
      66
    ],
    "3774c872": [
      43,
      22,
      55,
      61,
      63,
      65,
      67,
      60,
      62,
      64,
      66
    ],
    "f07c2f22": [
      43,
      22,
      55,
      61,
      63,
      65,
      67,
      60,
      62,
      64,
      66
    ],
    "4317a802": [
      43,
      22,
      55,
      61,
      63,
      65,
      67,
      60,
      62,
      64,
      66
    ],
    "c015dde4": [
      43,
      22,
      55,
      61,
      63,
      65,
      67,
      60,
      62,
      64,
      66
    ],
    "f800fc30": [
      43,
      22,
      55,
      61,
      63,
      65,
      67,
      60,
      62,
      64,
      66
    ],
    "2be16fe4": [
      43,
      22,
      55,
      61,
      63,
      65,
      67,
      60,
      62,
      64,
      66
    ],
    "f657e984": [
      43,
      22,
      55,
      61,
      63,
      65,
      67,
      60,
      62,
      64,
      66
    ],
    "21e54410": [
      43,
      22,
      55,
      61,
      63,
      65,
      67,
      60,
      62,
      64,
      66
    ],
    "139ea96b": [
      43,
      22,
      55,
      61,
      63,
      65,
      67,
      60,
      62,
      64,
      66
    ],
    "c915117e": [
      43,
      22,
      55,
      61,
      63,
      65,
      67,
      60,
      62,
      64,
      66
    ],
    "0e22c323": [
      2
    ],
    "4b8cca64": [
      2
    ],
    "72fa39c8": [
      2
    ],
    "a7b87002": [
      2
    ],
    "5ed66dff": [
      42,
      15,
      58,
      54
    ],
    "2d6b7899": [
      49,
      3,
      67,
      66,
      68,
      69,
      59
    ],
    "24c74813": [
      30,
      9
    ],
    "7100082b": [
      48,
      14
    ],
    "391825ce": [
      34,
      51,
      57,
      56
    ],
    "2f50362a": [
      2
    ],
    "f3d431a8": [
      42,
      15,
      58,
      54
    ],
    "847e36d6": [
      42,
      15,
      58,
      54
    ],
    "c56aa7d2": [
      42,
      15,
      58,
      54
    ],
    "6bdfb6b1": [
      49,
      3,
      67,
      66,
      68,
      69,
      59
    ],
    "743eba2b": [
      30,
      9
    ],
    "20c08b13": [
      48,
      14
    ],
    "c391a834": [
      34,
      51,
      57,
      56
    ],
    "09fddbbd": [
      6
    ],
    "68b9b1ab": [
      5
    ],
    "78f7ccc0": [
      42,
      15,
      58,
      54
    ],
    "3b0ef5c6": [
      42,
      15,
      58,
      54
    ],
    "7960c3ea": [
      42,
      15,
      58,
      54
    ],
    "2963f99c": [
      42,
      15,
      58,
      54
    ],
    "8c31f980": [
      42,
      15,
      58,
      54
    ],
    "252f6122": [
      37,
      12
    ],
    "131f717a": [
      37,
      12
    ],
    "4aee8edb": [
      37,
      12
    ],
    "7f7a5060": [
      37,
      12
    ],
    "fa3b5e9e": [
      37,
      12
    ],
    "195d2026": [
      44,
      52
    ],
    "aff4690a": [
      44,
      52
    ],
    "e792634c": [
      44,
      52
    ],
    "c161a036": [
      44,
      52
    ],
    "52bb4744": [
      44,
      52
    ],
    "49e6fb15": [
      49,
      3,
      67,
      66,
      68,
      69,
      59
    ],
    "002c7422": [
      49,
      3,
      67,
      66,
      68,
      69,
      59
    ],
    "252c2196": [
      49,
      3,
      67,
      66,
      68,
      69,
      59
    ],
    "22fd1010": [
      49,
      3,
      67,
      66,
      68,
      69,
      59
    ],
    "2df02e8b": [
      49,
      3,
      67,
      66,
      68,
      69,
      59
    ],
    "263b6cb1": [
      30,
      9
    ],
    "3caa57a0": [
      30,
      9
    ],
    "49020a99": [
      30,
      9
    ],
    "58e405f4": [
      30,
      9
    ],
    "530caeef": [
      30,
      9
    ],
    "6b6ff98e": [
      48,
      14
    ],
    "7c18d09e": [
      48,
      14
    ],
    "18afcba7": [
      48,
      14
    ],
    "3a142b08": [
      48,
      14
    ],
    "946c8ade": [
      48,
      14
    ],
    "cea0b0f6": [
      34,
      51,
      57,
      56
    ],
    "4d0ca846": [
      34,
      51,
      57,
      56
    ],
    "228f20c5": [
      34,
      51,
      57,
      56
    ],
    "12983d1c": [
      34,
      51,
      57,
      56
    ],
    "6315601b": [
      34,
      51,
      57,
      56
    ],
    "4ab1fed0": [
      6
    ],
    "d993d370": [
      6
    ],
    "831f790a": [
      6
    ],
    "eda8acf6": [
      16
    ],
    "483f3efd": [
      16
    ],
    "55716fa5": [
      53
    ],
    "c414f1c6": [
      53
    ],
    "5786e7e3": [
      38,
      27
    ],
    "25e6fc98": [
      43,
      22,
      55,
      61,
      63,
      65,
      67,
      60,
      62,
      64,
      66
    ],
    "6804dccf": [
      43,
      22,
      55,
      61,
      63,
      65,
      67,
      60,
      62,
      64,
      66
    ],
    "2982574a": [
      43,
      22,
      55,
      61,
      63,
      65,
      67,
      60,
      62,
      64,
      66
    ],
    "401f7166": [
      43,
      22,
      55,
      61,
      63,
      65,
      67,
      60,
      62,
      64,
      66
    ],
    "53936be4": [
      43,
      22,
      55,
      61,
      63,
      65,
      67,
      60,
      62,
      64,
      66
    ],
    "68d435f2": [
      42,
      15,
      58,
      54
    ],
    "1f66527e": [
      34,
      51,
      57,
      56
    ],
    "2c2c42f4": [
      30,
      9
    ],
    "c7e04b50": [
      48,
      14
    ],
    "3769408c": [
      49,
      3,
      67,
      66,
      68,
      69,
      59
    ]
  },
  "assetsMapping": {
    "bba68bf6": [
      "09b4e1f.js",
      "1fc29d5.js",
      "2083a7f.js",
      "5369629.js",
      "ef9c136.js"
    ],
    "28f3d6be": [
      "0e0f354.js"
    ],
    "05439b62": [
      "1e44eef.js"
    ],
    "6fca0322": [
      "21a6f93.js"
    ],
    "0e82c608": [
      "2c8df9b.js"
    ],
    "5aaf7b86": [
      "3288e1a.js"
    ],
    "9bcd6b58": [
      "359c5f1.js"
    ],
    "5cf9e718": [
      "3631729.js"
    ],
    "6a58ccfb": [
      "381cff8.js"
    ],
    "4209e522": [
      "4439e6a.js"
    ],
    "1eecd606": [
      "4f381d3.js"
    ],
    "2aff1868": [
      "4fe7336.js"
    ],
    "1598dcde": [
      "5d22f7a.js"
    ],
    "33c1e4ec": [
      "5e0ac24.js"
    ],
    "83ccce72": [
      "639cbc2.js"
    ],
    "4036942c": [
      "7481c7a.js"
    ],
    "2206c921": [
      "772f257.js"
    ],
    "1a3ae26b": [
      "87ca3e7.js"
    ],
    "085a35c4": [
      "8f935e8.js"
    ],
    "616f55a4": [
      "a809158.js"
    ],
    "b8aedc4a": [
      "b781eec.js"
    ],
    "7ea24c87": [
      "c92aa27.js"
    ],
    "ef00878e": [
      "c9697ac.js"
    ],
    "8d134c8e": [
      "d5539ee.js"
    ],
    "2a130dde": [
      "db80ac9.js"
    ],
    "c228672c": [
      "e055d4c.js"
    ]
  }
}